{
    "accentColor": "#2b6680",
    "backgroundColor": "#f2f2f7",
    "backgroundColorDeep": "#f6f6f9",
    "barColor": "#ececf2",
    "bigSidebarLogo": "dex-logo-sidebar.png",
    "buttonColorDisabled": "#f9f9fb",
    "buttonColorEnabled": "#f2f2f7",
    "buttonColorHovered": "#efeff5",
    "buttonColorTextDisabled": "#777777",
    "buttonColorTextEnabled": "#405366",
    "buttonColorTextHovered": "#405366",
    "chartTheme": "light",
    "chartGridLineColor":"#707070",
    "chartTradingLineBackgroundColor": "#e3f2fd",
    "chartTradingLineColor": "#37a6ef",
    "colorInnerShadowBottom": "#dddddd",
    "colorInnerShadowTop": "#efefef",
    "colorLineGradient1": "#eef1f7",
    "colorLineGradient2": "#dce1e8",
    "colorLineGradient3": "#eef1f7",
    "colorLineGradient4": "#dce1e8",
    "colorSidebarDropShadow": "#becde2",
    "colorThemeDarkLight": "#456078",
    "dexBoxBackgroundColor": "#f9f9fb",
    "floatBoxShadowDark": "#becde2",
    "floatShadow1": "#21ffffff",
    "floatShadow2": "#60ffffff",
    "foregroundColor": "#405366",
    "greenColor": "#109f8d",
    "hightlightColor": "#ececf2",
    "innerShadowColor": "#becde2",
    "navigationSideBarButtonGradient1": "#8b95ed",
    "navigationSideBarButtonGradient2": "#ad7faaf0",
    "navigationSideBarButtonGradient3": "#a06dc9f3",
    "navigationSideBarButtonGradient4": "#006bcef4",
    "primaryColor": "#171a2c",
    "redColor": "#9a1165",
    "sideBarGradient1": "#f9f9fb",
    "sideBarGradient2": "#ececf2",
    "smallSidebarLogo": "dex-logo.png",
    "surfaceColor": "#f6f6f9",
    "textPlaceHolderColor": "#8e9293",
    "textSelectedColor": "#f9f9fb",
    "textSelectionColor": "#14bca6",
    "whiteblack": "#000000"
}
