{
    "accentColor": "#F0F2FF",
    "foregroundColor": "#456078",
    "backgroundColor": "#FCFCFC",
    "backgroundColorDeep": "#FCFCFC",

    "buttonColorDisabled": "#D8E3F8",
    "buttonColorEnabled": "#F0F6FF",
    "buttonColorHovered": "#D7E7FF",
    "buttonColorPressed": "#B8D2F9",
    "buttonTextDisabledColor": "#D1D4DC",
    "buttonTextEnabledColor": "#456078",
    "buttonTextHoveredColor": "#2F5678",
    "buttonTextPressedColor": "#3A5B78",

    "gradientButtonStartColor": "#5A68E6",
    "gradientButtonEndColor": "#4986EAAB",
    "gradientButtonDisabledStartColor": "#CDD0F6",
    "gradientButtonDisabledEndColor": "#DAE5F9",
    "gradientButtonHoveredStartColor": "#5A68E6",
    "gradientButtonHoveredEndColor": "#5A68E6",
    "gradientButtonPressedStartColor": "#6A4DE3",
    "gradientButtonPressedEndColor": "#6A4DE3",
    "gradientButtonTextEnabledColor": "#FFF",
    "gradientButtonTextDisabledColor": "#FFF",
    "gradientButtonTextHoveredColor": "#FFF",
    "gradientButtonTextPressedColor": "#FFF",

    "checkBoxGradientStartColor": "#8892EB",
    "checkBoxGradientEndColor": "#9DD4F3",

    "switchGradientStartColor": "#8892EB",
    "switchGradientEndColor": "#9DD4F3",
    "switchGradientStartColor2": "#FFF",
    "switchGradientEndColor2": "#FFF",

    "comboBoxBackgroundColor": "#FFFFFFFF",
    "comboBoxArrowsColor": "#456078FF",
    "comboBoxDropdownItemHighlightedColor": "#456078FF",

    "modalPageCounterGradientStartColor": "#9DD4F3",
    "modalPageCounterGradientEndColor": "#9DD4F3",

    "notifPopupBackgroundColor": "#EDF4FFFF",
    "notifPopupTextColor": "#456078FF",
    "notifPopupTimerColor": "#DBE0E4FF",
    "notifPopupTimerBackgroundColor": "#93A3B1FF",
    "notifPopupIconStartColor": "#000000FF",
    "notifPopupIconEndColor": "#000000FF",

    "scrollBarIndicatorColor": "#DBE0E4FF",
    "scrollBarBackgroundColor": "#93A3B1FF",

    "tabSelectedColor": "#DCE8FD",

    "textDisabledColor": "#C5CFD8",
    "textSelectionColor": "#14bca6",
    "textPlaceholderColor": "#91A8E8",
    "textSelectedColor": "#f9f9fb",

    "textFieldBackgroundColor": "#F3F5F6FF",
    "textFieldPrefixColor": "#45607894",
    "textFieldSuffixColor": "#456078FF",

    "chartTradingLineBackgroundColor": "#C5F2EF",
    "chartTradingLineColor": "#53EBD7",

    "innerBackgroundColor": "#edf4ff",

    "floatingBackgroundColor": "#edf4ff",

    "rangeSliderBackgroundColor": "#5A68E6FF",
    "rangeSliderDistanceColor": "#4986EA3B",
    "rangeSliderIndicatorBackgroundStartColor": "#5A68E6FF",
    "rangeSliderIndicatorBackgroundEndColor": "#4986EAFF",

    "sidebarBgColor": "#FCFCFC",
    "sidebarVersionTextColor": "#456078",
    "sidebarCursorStartColor": "#5A68E6",
    "sidebarCursorEndColor": "#2CB9F000",
    "sidebarLineTextHovered": "#2C87B9",

    "tradeBuyModeSelectorBackgroundColorStart": "#6A4DE3FF",
    "tradeBuyModeSelectorBackgroundColorEnd": "#2279F1FF",
    "tradeSellModeSelectorBackgroundColorStart": "#E52167FF",
    "tradeSellModeSelectorBackgroundColorEnd": "#E216A9FF",
    "tradeMarketModeSelectorNotSelectedBackgroundColor": "#89B6FF21",

    "okColor": "#00C058",
    "noColor": "#E52167",

    "arrowUpColor": "#F85757",
    "arrowDownColor": "#845FEF",

    "lineSeparatorColor": "#CDD3DC"
}
